japronto_extra.py
japronto_extra-0.1.3.dist-info/METADATA
japronto_extra-0.1.3.dist-info/WHEEL
japronto_extra-0.1.3.dist-info/top_level.txt
japronto_extra-0.1.3.dist-info/RECORD
