Metadata-Version: 2.1
Name: japronto-extra
Version: 0.1.3
Summary: A bit of sugar for the [fastest python framework][japronto]
Home-page: https://github.com/imbolc/japronto_extra
Author: Imbolc
Author-email: imbolc@imbolc.name
License: ISC
Platform: UNKNOWN
Classifier: Development Status :: 4 - Beta
Classifier: Intended Audience :: Developers
Classifier: License :: OSI Approved :: ISC License (ISCL)
Classifier: Programming Language :: Python
Classifier: Programming Language :: Python :: 3
